<?xml version="1.0" encoding="UTF-8"?>
<doublecmd>
  <History>
    <Navigation>
      <Item>/home/petr/Repo/selektor-detailu.heluz.cz/</Item>
      <Item>/home/petr/Repo/selektor-detailu.heluz.cz/files/</Item>
      <Item>/home/petr/GoogleDrive/Zalohy/</Item>
      <Item>/home/petr/GoogleDrive/</Item>
      <Item>/home/petr/</Item>
      <Item>/home/petr/Stažené/</Item>
      <Item>/home/</Item>
      <Item>/</Item>
      <Item>/bin/</Item>
      <Item>/usr/</Item>
      <Item>/usr/lib/</Item>
    </Navigation>
    <CommandLine/>
    <FileMask/>
    <VolumeSize/>
    <CreateDirectories/>
    <SearchText/>
    <SearchTextPath/>
    <ReplaceText/>
    <ReplaceTextPath/>
    <RenameNameMask/>
    <RenameExtMask/>
    <SearchDirectories/>
    <SearchExcludeFiles/>
    <SearchExcludeDirectories/>
  </History>
</doublecmd>
