[
    {
        "name": "Spotify",
        "alias": null,
        "tag_start": null,
        "tag_end": null,
        "display_name": null,
        "on_return": null,
        "next_content": null,
        "type": "audio_sink",
        "priority": 1.0,
        "exit": true,
        "shortcut": true,
        "spawn_focus": false,
        "async": true,
        "home": "OnlyHome",
        "args": {},
        "binds": [
            {
                "bind": "Return",
                "callback": "playpause",
                "exit": false
            },
            {
                "bind": "l",
                "callback": "next",
                "exit": false
            },
            {
                "bind": "h",
                "callback": "previous",
                "exit": false
            }
        ],
        "actions": [
            {
                "name": "Skip",
                "exec": null,
                "icon": "media-seek-forward",
                "method": "inner.next",
                "exit": false
            },
            {
                "name": "Previous",
                "exec": null,
                "icon": "media-seek-backward",
                "method": "inner.previous",
                "exit": false
            }
        ],
        "add_actions": null
    },
    {
        "name": "Calculator",
        "alias": null,
        "tag_start": null,
        "tag_end": null,
        "display_name": null,
        "on_return": "copy",
        "next_content": null,
        "type": "calculation",
        "priority": 1.0,
        "exit": true,
        "shortcut": true,
        "spawn_focus": true,
        "async": false,
        "home": "Search",
        "args": {
            "capabilities": [
                "calc.math",
                "calc.units"
            ]
        },
        "binds": null,
        "actions": null,
        "add_actions": null
    },
    {
        "name": "App Launcher",
        "alias": "app",
        "tag_start": null,
        "tag_end": null,
        "display_name": null,
        "on_return": null,
        "next_content": null,
        "type": "app_launcher",
        "priority": 3.0,
        "exit": true,
        "shortcut": true,
        "spawn_focus": true,
        "async": false,
        "home": "Home",
        "args": {},
        "binds": null,
        "actions": null,
        "add_actions": null
    },
    {
        "name": "Kill Process",
        "alias": "kill",
        "tag_start": null,
        "tag_end": null,
        "display_name": null,
        "on_return": null,
        "next_content": null,
        "type": "process",
        "priority": 0.0,
        "exit": true,
        "shortcut": true,
        "spawn_focus": true,
        "async": false,
        "home": "Search",
        "args": {},
        "binds": null,
        "actions": null,
        "add_actions": null
    },
    {
        "name": "DuckDuckGo Search",
        "alias": "d:",
        "tag_start": "{keyword}",
        "tag_end": null,
        "display_name": "DuckDuckGo",
        "on_return": null,
        "next_content": null,
        "type": "web_launcher",
        "priority": 90.0,
        "exit": true,
        "shortcut": true,
        "spawn_focus": true,
        "async": false,
        "home": "Search",
        "args": {
            "icon": "duckduckgo",
            "search_engine": "https://duckduckgo.com/?q={keyword}"
        },
        "binds": null,
        "actions": null,
        "add_actions": null
    },
    {
        "name": "Reddit Search",
        "alias": "r:",
        "tag_start": "{keyword}",
        "tag_end": null,
        "display_name": "Reddit Search",
        "on_return": null,
        "next_content": null,
        "type": "web_launcher",
        "priority": 91.0,
        "exit": true,
        "shortcut": true,
        "spawn_focus": true,
        "async": false,
        "home": "Search",
        "args": {
            "icon": "reddit",
            "search_engine": "https://www.google.com/search?q=site:reddit.com+{keyword}&udm=14&tbm=web"
        },
        "binds": null,
        "actions": null,
        "add_actions": null
    },
    {
        "name": "Perplexity Search",
        "alias": "p:",
        "tag_start": "{keyword}",
        "tag_end": null,
        "display_name": "Perplexity AI",
        "on_return": null,
        "next_content": null,
        "type": "web_launcher",
        "priority": 92.0,
        "exit": true,
        "shortcut": true,
        "spawn_focus": true,
        "async": false,
        "home": "Search",
        "args": {
            "icon": "perplexity",
            "search_engine": "https://www.perplexity.ai/search?focus=internet&q={keyword}"
        },
        "binds": null,
        "actions": null,
        "add_actions": null
    },
    {
        "name": "YouTube Search",
        "alias": "y:",
        "tag_start": "{keyword}",
        "tag_end": null,
        "display_name": "YouTube",
        "on_return": null,
        "next_content": null,
        "type": "web_launcher",
        "priority": 93.0,
        "exit": true,
        "shortcut": true,
        "spawn_focus": true,
        "async": false,
        "home": "Search",
        "args": {
            "icon": "youtube",
            "search_engine": "https://www.youtube.com/results?search_query={keyword}"
        },
        "binds": null,
        "actions": null,
        "add_actions": null
    },
    {
        "name": "Web Search",
        "alias": "g:",
        "tag_start": "{keyword}",
        "tag_end": null,
        "display_name": "Google Search",
        "on_return": null,
        "next_content": null,
        "type": "web_launcher",
        "priority": 94.0,
        "exit": true,
        "shortcut": true,
        "spawn_focus": true,
        "async": false,
        "home": "Search",
        "args": {
            "icon": "google",
            "search_engine": "https://www.google.com/search?q={keyword}&udm=14&tbm=web"
        },
        "binds": null,
        "actions": null,
        "add_actions": null
    },
    {
        "alias": "em",
        "tag_start": "{keyword}",
        "name": "Emoji Picker",
        "type": "emoji_picker",
        "args": {
            "default_skin_tone": "Simpsons"
        },
        "priority": 1.0,
        "home": "Search"
    }
]